pivotpy/__init__.py
pivotpy/_nbdev.py
pivotpy/api.py
pivotpy/cli.py
pivotpy/g_utils.py
pivotpy/i_plots.py
pivotpy/iplots.py
pivotpy/parser.py
pivotpy/s_plots.py
pivotpy/serializer.py
pivotpy/sio.py
pivotpy/splots.py
pivotpy/styles.py
pivotpy/surfaces.py
pivotpy/utils.py
pivotpy/vr_parser.py
pivotpy/widgets.py
pivotpy-1.3.11.dist-info/LICENSE
pivotpy-1.3.11.dist-info/METADATA
pivotpy-1.3.11.dist-info/WHEEL
pivotpy-1.3.11.dist-info/entry_points.txt
pivotpy-1.3.11.dist-info/top_level.txt
pivotpy-1.3.11.dist-info/RECORD
