Metadata-Version: 2.1
Name: pivotpy
Version: 1.3.11
Summary: A description of your project
Home-page: https://github.com/massgh/pivotpy/tree/master/
Author: Abdul Saboor
Author-email: mass_qau@outlook.com
License: Apache Software License 2.0
Keywords: dft vasp visualization
Platform: UNKNOWN
Classifier: Development Status :: 5 - Production/Stable
Classifier: Intended Audience :: Developers
Classifier: License :: OSI Approved :: Apache Software License
Classifier: Natural Language :: English
Classifier: Programming Language :: Python :: 3.6
Classifier: Programming Language :: Python :: 3.7
Classifier: Programming Language :: Python :: 3.8
Requires-Python: >=3.6
License-File: LICENSE
Requires-Dist: ipyvasp
Requires-Dist: plotly
Requires-Dist: ipywidgets
Requires-Dist: numpy
Requires-Dist: matplotlib (==3.4.0)
Requires-Dist: scipy
Requires-Dist: pandas
Requires-Dist: requests
